Metadata-Version: 2.1
Name: msdk
Version: 0.0.0.2
Summary: SDK for Malcore API
Home-page: https://github.com/Internet-2-0/Malcore-SDK
Author: Thomas Perkins
Author-email: contact@malcore.io
License-File: LICENSE.md
